extendable_json/__init__.py
extendable_json/exception_serialization.py
extendable_json/extendable_json.py
extendable_json/extensions.py
extendable_json/version.py
Extendable_JSON-0.0.1.dist-info/LICENSE
Extendable_JSON-0.0.1.dist-info/METADATA
Extendable_JSON-0.0.1.dist-info/WHEEL
Extendable_JSON-0.0.1.dist-info/top_level.txt
Extendable_JSON-0.0.1.dist-info/RECORD
