Metadata-Version: 2.1
Name: Extendable-JSON
Version: 0.0.1
Summary: Drop in replacement of json, to quickly extend serializing capabilities
Home-page: https://github.com/Kiln707/extendable_json
Author: Steven Swanson
Author-email: Steven@SwanOhana.net
License: UNKNOWN
Platform: UNKNOWN
Classifier: Programming Language :: Python :: 3
Classifier: License :: OSI Approved :: MIT License
Requires-Python: >=3.6
Requires-Dist: flask
